README.md
setup.py
HyperclassifierSearch/HyperclassifierSearch.py
HyperclassifierSearch/__init__.py
HyperclassifierSearch.egg-info/PKG-INFO
HyperclassifierSearch.egg-info/SOURCES.txt
HyperclassifierSearch.egg-info/dependency_links.txt
HyperclassifierSearch.egg-info/not-zip-safe
HyperclassifierSearch.egg-info/top_level.txt