Metadata-Version: 2.1
Name: HyperclassifierSearch
Version: 1.0
Summary: Train multiple classifiers/pipelines
Home-page: https://github.com/dabln/HyperclassifierSearch
Author: Jan Henner
Author-email: mail@janhenner.de
License: UNKNOWN
Platform: UNKNOWN
Classifier: Programming Language :: Python :: 3
Classifier: License :: OSI Approved :: MIT License
Classifier: Operating System :: OS Independent
Requires-Python: >=3.0
